semvecpy/__init__.py
semvecpy/permutations/__init__.py
semvecpy/permutations/constants.py
semvecpy/permutations/dense_permutations.py
semvecpy/permutations/dense_permutations_test.py
semvecpy/permutations/sparse_permutations.py
semvecpy/permutations/sparse_permutations_test.py
semvecpy/vectors/__init__.py
semvecpy/vectors/binary_bitvectors.py
semvecpy/vectors/binary_bitvectors_test.py
semvecpy/vectors/binary_packedbitvectors.py
semvecpy/vectors/binary_packedbitvectors_test.py
semvecpy/vectors/binary_vectors.py
semvecpy/vectors/binary_vectors_test.py
semvecpy/vectors/graded_vectors.py
semvecpy/vectors/graded_vectors_test.py
semvecpy/vectors/real_vectors.py
semvecpy/vectors/real_vectors_test.py
semvecpy/vectors/semvec_utils.py
semvecpy/vectors/semvec_utils_test.py
semvecpy/vectors/shm_binary_packedbitvectors.py
semvecpy/vectors/vector_utils.py
semvecpy/vectors/vector_utils_test.py
semvecpy-0.1.26.dist-info/AUTHORS
semvecpy-0.1.26.dist-info/LICENSE.txt
semvecpy-0.1.26.dist-info/METADATA
semvecpy-0.1.26.dist-info/WHEEL
semvecpy-0.1.26.dist-info/top_level.txt
semvecpy-0.1.26.dist-info/RECORD
