Metadata-Version: 2.1
Name: semvecpy
Version: 0.1.26
Summary: Semantic Vectors work in Python
Home-page: https://github.com/semanticvectors/semvecpy
Author: Semantic Vectors Authors
Author-email: semanticvectors@googlegroups.com
License: UNKNOWN
Platform: UNKNOWN
Classifier: Programming Language :: Python :: 3
Classifier: License :: OSI Approved :: BSD License
Classifier: Operating System :: OS Independent
Requires-Python: >=3
Requires-Dist: bitarray
Requires-Dist: multiprocess
Requires-Dist: numba
Requires-Dist: numpy
Requires-Dist: scipy
